abacus_tpot/__init__.py
abacus_tpot/tpot_config.py
abacus_tpot-0.92.dist-info/DESCRIPTION.rst
abacus_tpot-0.92.dist-info/METADATA
abacus_tpot-0.92.dist-info/RECORD
abacus_tpot-0.92.dist-info/WHEEL
abacus_tpot-0.92.dist-info/metadata.json
abacus_tpot-0.92.dist-info/top_level.txt
abacus_tpot-0.92.dist-info/zip-safe
