Metadata-Version: 2.0
Name: abacus-tpot
Version: 0.92
Summary: TPOT's analysis library
Home-page: https://github.com/workforce-data-initiative/abacus-tpot
Author: Stanley Ndagi, Tom Plagge
Author-email: stanley@brighthive.io, tom@brighthive.io
License: Apache 2.0
Download-URL: https://github.com/workforce-data-initiative/abacus-tpot/archive/None.tar.gz
Keywords: analysis,data,tpot,library
Platform: UNKNOWN
